mdcat/__init__.py
mdcat/__main__.py
mdcat-1.0.0.dist-info/LICENSE
mdcat-1.0.0.dist-info/METADATA
mdcat-1.0.0.dist-info/WHEEL
mdcat-1.0.0.dist-info/entry_points.txt
mdcat-1.0.0.dist-info/top_level.txt
mdcat-1.0.0.dist-info/RECORD
