Metadata-Version: 2.1
Name: mdcat
Version: 1.0.0
Summary: Markdown-friendly variant of cat
Home-page: https://github.com/hubpav/mdcat
Author: Pavel Hübner
Author-email: pavel.hubner@gmail.com
License: MIT
Keywords: markdown cat dump file
Platform: any
Classifier: Development Status :: 5 - Production/Stable
Classifier: Environment :: Console
Classifier: Intended Audience :: Developers
Classifier: License :: OSI Approved :: MIT License
Classifier: Natural Language :: English
Classifier: Operating System :: OS Independent
Classifier: Programming Language :: Python :: 3
Classifier: Topic :: Utilities
Requires-Dist: click (==7.0)
